<?xml version="1.0" encoding="UTF-8"?>
<web-fragment version="3.1" id="TelveCoreWebFragment" 
              xmlns="http://xmlns.jcp.org/xml/ns/javaee" 
              xmlns:xsi="http://www.w3.org/2001/XMLSchema-instance" 
              xsi:schemaLocation="http://xmlns.jcp.org/xml/ns/javaee http://xmlns.jcp.org/xml/ns/javaee/web-fragment_3_1.xsd">

    
    <context-param>
        <param-name>javax.faces.PROJECT_STAGE</param-name>
        <param-value>Development</param-value>
    </context-param>
    <context-param>
        <param-name>primefaces.CLIENT_SIDE_VALIDATION</param-name>
        <param-value>true</param-value>
    </context-param>
    <context-param>
        <param-name>primefaces.FONT_AWESOME</param-name>
        <param-value>true</param-value>
    </context-param>
    
    <context-param>
        <param-name>primefaces.THEME</param-name>
        <param-value>#{themeSelector.theme}</param-value>
    </context-param>
        
    <context-param>
        <param-name>primefaces.UPLOADER</param-name>
        <param-value>native</param-value>
    </context-param>
    <context-param>
        <param-name>javax.faces.DATETIMECONVERTER_DEFAULT_TIMEZONE_IS_SYSTEM_TIMEZONE</param-name>
        <param-value>true</param-value>
    </context-param>
    <!-- JCache Provider ve ya Infinispan Provider lazım -->
    <context-param>
        <param-name>primefaces.CACHE_PROVIDER</param-name>
        <param-value>org.primefaces.cache.JCacheProvider</param-value>
    </context-param>
    
    <servlet>
        <servlet-name>Push Servlet</servlet-name>
        <servlet-class>org.primefaces.push.PushServlet</servlet-class>
        <init-param>
            <param-name>org.atmosphere.cpr.broadcasterCacheClass</param-name>
            <param-value>org.atmosphere.cache.UUIDBroadcasterCache</param-value>
        </init-param>
        <async-supported>true</async-supported>
    </servlet>
    <servlet-mapping>
        <servlet-name>Push Servlet</servlet-name>
        <url-pattern>/primepush/*</url-pattern>
    </servlet-mapping>
    
    <servlet-mapping>
        <servlet-name>javax.ws.rs.core.Application</servlet-name>
        <url-pattern>/rest/*</url-pattern>
    </servlet-mapping>
    
    <servlet>
        <servlet-name>Faces Servlet</servlet-name>
        <servlet-class>javax.faces.webapp.FacesServlet</servlet-class>
        <load-on-startup>1</load-on-startup>
    </servlet>
    <servlet-mapping>
        <servlet-name>Faces Servlet</servlet-name>
        <url-pattern>*.jsf</url-pattern>
    </servlet-mapping>
    <session-config>
        <session-timeout>
            30
        </session-timeout>
    </session-config>
    <welcome-file-list>
        <welcome-file>index.html</welcome-file>
    </welcome-file-list>
    
    <mime-mapping>
        <extension>eot</extension>
        <mime-type>application/vnd.ms-fontobject</mime-type>
    </mime-mapping>
    <mime-mapping>  
        <extension>otf</extension>  
        <mime-type>font/opentype</mime-type>  
    </mime-mapping>      
    <mime-mapping>  
        <extension>ttf</extension>  
        <mime-type>application/x-font-ttf</mime-type>  
    </mime-mapping>      
    <mime-mapping>  
        <extension>woff</extension>  
        <mime-type>application/x-font-woff</mime-type>  
    </mime-mapping>
    <mime-mapping>  
        <extension>svg</extension>  
        <mime-type>image/svg+xml</mime-type>  
    </mime-mapping>


    <listener>
        <listener-class>org.apache.shiro.web.env.EnvironmentLoaderListener</listener-class>
    </listener>
    
    <filter>
        <filter-name>ShiroFilter</filter-name>
        <filter-class>org.apache.shiro.web.servlet.ShiroFilter</filter-class>
    </filter>

    <filter-mapping>
        <filter-name>ShiroFilter</filter-name>
        <url-pattern>/*</url-pattern>
        <dispatcher>REQUEST</dispatcher> 
        <dispatcher>FORWARD</dispatcher> 
        <dispatcher>INCLUDE</dispatcher> 
        <dispatcher>ERROR</dispatcher>
    </filter-mapping>
</web-fragment>